Metadata-Version: 1.1
Name: packerinspector-api
Version: 1.0.0
Summary: Deep Packer Inspector API
Home-page: https://github.com/7flying/packerinspector-api
Author: Deep Packer Inspector team
Author-email: packerinspector@deusto.es
License: GPLv3
Keywords: malware packers packerinspector deep packer inspector
Platform: UNKNOWN
Classifier: Development Status :: 5 - Production/Stable
Classifier: Intended Audience :: Developers
Classifier: Intended Audience :: Science/Research
Classifier: Natural Language :: English
Classifier: Topic :: Security
Classifier: License :: OSI Approved :: GNU General Public License v3 (GPLv3)
Classifier: Programming Language :: Python :: 2.7
Classifier: Programming Language :: Python :: 3.5
